{
  "stories": [
    {
      "id": "epitimya",
      "title": "Епитимья",
      "date": "2025-08-01",
      "minutes": 11,
      "tags": [
        "Кайрнакс",
        "DOMINUS",
        "этика"
      ],
      "arc": "dominus",
      "text": "ТЕКСТЧТОЛИ"
    },
    {
      "id": "dorogovato",
      "title": "Дороговато",
      "date": "2025-07-25",
      "minutes": 10,
      "tags": [
        "Кайрнакс",
        "линии",
        "R-сектор"
      ],
      "arc": "lines",
      "text": "ЗАГЛУШКА: ВСТАВИТЬ ТЕКСТ (Дороговато)"
    },
    {
      "id": "chelovecheskiy-faktor",
      "title": "Человеческий фактор",
      "date": "2025-07-23",
      "minutes": 9,
      "tags": [
        "Кайрнакс",
        "инженерия"
      ],
      "arc": "infra",
      "text": "ЗАГЛУШКА: ВСТАВИТЬ ТЕКСТ (Человеческий фактор)"
    },
    {
      "id": "ibut-g1",
      "title": "ИБУТ — глава 1",
      "date": "2025-08-08",
      "minutes": 8,
      "tags": [
        "ИБУТ",
        "попаданцы"
      ],
      "arc": "ibut",
      "text": "ЗАГЛУШКА: ВСТАВИТЬ ТЕКСТ (ИБУТ — глава 1)"
    },
    {
      "id": "ibut-g2",
      "title": "ИБУТ — глава 2",
      "date": "2025-08-08",
      "minutes": 8,
      "tags": [
        "ИБУТ",
        "попаданцы"
      ],
      "arc": "ibut",
      "text": "ЗАГЛУШКА: ВСТАВИТЬ ТЕКСТ (ИБУТ — глава 2)"
    }
  ]
}
